timeflux/__init__.py
timeflux/__main__.py
timeflux/timeflux.py
timeflux/version.py
timeflux/core/__init__.py
timeflux/core/branch.py
timeflux/core/exceptions.py
timeflux/core/graph.py
timeflux/core/io.py
timeflux/core/logging.py
timeflux/core/manager.py
timeflux/core/message.py
timeflux/core/node.py
timeflux/core/registry.py
timeflux/core/scheduler.py
timeflux/core/sync.py
timeflux/core/validate.py
timeflux/core/worker.py
timeflux/estimators/__init__.py
timeflux/estimators/classifiers/__init__.py
timeflux/estimators/transformers/__init__.py
timeflux/estimators/transformers/shape.py
timeflux/helpers/__init__.py
timeflux/helpers/background.py
timeflux/helpers/bdf.py
timeflux/helpers/clock.py
timeflux/helpers/handler.py
timeflux/helpers/hdf5.py
timeflux/helpers/lsl.py
timeflux/helpers/mne.py
timeflux/helpers/port.py
timeflux/helpers/testing.py
timeflux/helpers/viz.py
timeflux/nodes/__init__.py
timeflux/nodes/accumulate.py
timeflux/nodes/apply.py
timeflux/nodes/axis.py
timeflux/nodes/debug.py
timeflux/nodes/dejitter.py
timeflux/nodes/epoch.py
timeflux/nodes/events.py
timeflux/nodes/expression.py
timeflux/nodes/gate.py
timeflux/nodes/hdf5.py
timeflux/nodes/lsl.py
timeflux/nodes/ml.py
timeflux/nodes/monitor.py
timeflux/nodes/osc.py
timeflux/nodes/query.py
timeflux/nodes/random.py
timeflux/nodes/sequence.py
timeflux/nodes/window.py
timeflux/nodes/xarray.py
timeflux/nodes/zmq.py
timeflux/schema/app.json
timeflux-0.17.2.dist-info/LICENSE
timeflux-0.17.2.dist-info/METADATA
timeflux-0.17.2.dist-info/WHEEL
timeflux-0.17.2.dist-info/entry_points.txt
timeflux-0.17.2.dist-info/top_level.txt
timeflux-0.17.2.dist-info/RECORD
