Metadata-Version: 2.1
Name: timeflux
Version: 0.17.2
Summary: Acquisition and real-time processing of biosignals
Home-page: https://timeflux.io
Author: Pierre Clisson
Author-email: contact@timeflux.io
License: MIT
Project-URL: Documentation, https://doc.timeflux.io
Project-URL: Source Code, https://github.com/timeflux/timeflux
Project-URL: Bug Tracker, https://github.com/timeflux/timeflux/issues
Keywords: time series,machine learning,biosignals,brain-computer interface,BCI,EEG,ECG,PPG,EMG,EDA,GSR
Classifier: Development Status :: 4 - Beta
Classifier: Environment :: Console
Classifier: Intended Audience :: Developers
Classifier: Intended Audience :: Science/Research
Classifier: License :: OSI Approved :: MIT License
Classifier: Operating System :: OS Independent
Classifier: Programming Language :: Python
License-File: LICENSE
Requires-Dist: networkx==2.5.1
Requires-Dist: PyYAML>=5.1
Requires-Dist: numpy==1.26.4
Requires-Dist: pandas>=0.25
Requires-Dist: xarray>=0.14
Requires-Dist: bottleneck>=1.3
Requires-Dist: scipy>=1.3
Requires-Dist: pyzmq>=18.1
Requires-Dist: coloredlogs>=10.0
Requires-Dist: tables>=3.6
Requires-Dist: Cython>=0.29.6
Requires-Dist: pylsl>=1.12.2
Requires-Dist: python-osc>=1.7.0
Requires-Dist: python-dotenv>=0.10
Requires-Dist: jsonschema>=3.0
Requires-Dist: scikit-learn>=0.21.3
Requires-Dist: Jinja2>=2.11
Requires-Dist: colorama>=0.4.4
Provides-Extra: opt
Requires-Dist: graphviz>=0.13; extra == "opt"
Requires-Dist: mne>=0.23; extra == "opt"
Requires-Dist: pyedflib>=0.1.22; extra == "opt"
Provides-Extra: dev
Requires-Dist: pytest>=5.3; extra == "dev"
Requires-Dist: sphinx>=2.2; extra == "dev"
Requires-Dist: sphinx_rtd_theme>=0.4; extra == "dev"
Requires-Dist: setuptools_scm; extra == "dev"
Requires-Dist: docinit; extra == "dev"
Requires-Dist: black; extra == "dev"
